winzy_checkmail/__init__.py
winzy_checkmail-0.1.dist-info/LICENSE
winzy_checkmail-0.1.dist-info/METADATA
winzy_checkmail-0.1.dist-info/WHEEL
winzy_checkmail-0.1.dist-info/entry_points.txt
winzy_checkmail-0.1.dist-info/top_level.txt
winzy_checkmail-0.1.dist-info/RECORD
