Metadata-Version: 2.1
Name: winzy-checkmail
Version: 0.1
Summary: Access outlook email using cli.
Author: Sukhbinder Singh
License: Apache-2.0
Project-URL: Homepage, https://github.com/sukhbinder/winzy-checkmail
Project-URL: Changelog, https://github.com/sukhbinder/winzy-checkmail/releases
Project-URL: Issues, https://github.com/sukhbinder/winzy-checkmail/issues
Project-URL: CI, https://github.com/sukhbinder/winzy-checkmail/actions
Classifier: License :: OSI Approved :: Apache Software License
License-File: LICENSE
Requires-Dist: winzy
Requires-Dist: pywin32
Provides-Extra: test
Requires-Dist: pytest ; extra == 'test'
